{
  "name": "titan",
  "title": "Titan",
  "description": "The Titan system for FoundryVTT!",
  "version": "1.0.0",
  "minimumCoreVersion": "0.9.0",
  "compatibleCoreVersion": "10",
  "author": "Solidor",
  "esmodules": ["module/titan.mjs"],
  "styles": ["css/titan.css"],
  "scripts": [],
  "packs": [],
  "languages": [
    {
      "lang": "en",
      "name": "English",
      "path": "lang/en.json"
    }
  ],
  "gridDistance": 1,
  "gridUnits": "m",
  "primaryTokenAttribute": "stamina",
  "secondaryTokenAttribute": "wounds",
  "url": "",
  "manifest": "",
  "download": "",
  "license": "LICENSE.txt"
}
